{
  "editions": 161,
  "totalWords": 742431,
  "avgWords": 4611,
  "longest": {
    "slug": "monday-march-9th",
    "date": "2026-03-09",
    "title": "Monday, March 9th",
    "words": 7703
  },
  "firstDate": "2025-02-03",
  "lastDate": "2026-07-11",
  "stories": 1564,
  "triviaCount": 14,
  "openings": 60,
  "closings": 19,
  "topSources": [
    [
      "sevendaysvt.com",
      418
    ],
    [
      "wcax.com",
      350
    ],
    [
      "vtdigger.org",
      213
    ],
    [
      "vermontbiz.com",
      110
    ],
    [
      "mynbc5.com",
      91
    ],
    [
      "vtcng.com",
      73
    ],
    [
      "vermontpublic.org",
      51
    ],
    [
      "uvmathletics.com",
      41
    ],
    [
      "burlingtonfreepress.com",
      36
    ],
    [
      "vtcommunitynews.org",
      34
    ],
    [
      "mychamplainvalley.com",
      30
    ],
    [
      "vtcynic.com",
      24
    ]
  ],
  "monthly": [
    [
      "2025-02",
      {
        "editions": 12,
        "words": 22688
      }
    ],
    [
      "2025-03",
      {
        "editions": 7,
        "words": 16064
      }
    ],
    [
      "2025-04",
      {
        "editions": 9,
        "words": 22146
      }
    ],
    [
      "2025-05",
      {
        "editions": 9,
        "words": 27484
      }
    ],
    [
      "2025-06",
      {
        "editions": 8,
        "words": 28088
      }
    ],
    [
      "2025-07",
      {
        "editions": 8,
        "words": 36999
      }
    ],
    [
      "2025-08",
      {
        "editions": 7,
        "words": 30462
      }
    ],
    [
      "2025-09",
      {
        "editions": 8,
        "words": 39405
      }
    ],
    [
      "2025-10",
      {
        "editions": 10,
        "words": 43932
      }
    ],
    [
      "2025-11",
      {
        "editions": 10,
        "words": 40832
      }
    ],
    [
      "2025-12",
      {
        "editions": 11,
        "words": 50944
      }
    ],
    [
      "2026-01",
      {
        "editions": 10,
        "words": 51953
      }
    ],
    [
      "2026-02",
      {
        "editions": 11,
        "words": 63011
      }
    ],
    [
      "2026-03",
      {
        "editions": 9,
        "words": 59800
      }
    ],
    [
      "2026-04",
      {
        "editions": 10,
        "words": 64974
      }
    ],
    [
      "2026-05",
      {
        "editions": 10,
        "words": 66786
      }
    ],
    [
      "2026-06",
      {
        "editions": 9,
        "words": 57291
      }
    ],
    [
      "2026-07",
      {
        "editions": 3,
        "words": 19572
      }
    ]
  ],
  "topPlaces": [
    [
      "Burlington",
      12388
    ],
    [
      "South Burlington",
      1806
    ],
    [
      "UVM",
      1531
    ],
    [
      "Essex",
      1249
    ],
    [
      "Winooski",
      1215
    ],
    [
      "Church Street",
      1081
    ],
    [
      "Shelburne",
      1081
    ],
    [
      "Williston",
      691
    ],
    [
      "Flynn",
      622
    ],
    [
      "Higher Ground",
      575
    ],
    [
      "Colchester",
      523
    ],
    [
      "South End",
      307
    ],
    [
      "ECHO",
      302
    ],
    [
      "Lake Champlain",
      280
    ],
    [
      "Waterfront",
      254
    ]
  ],
  "topicCounts": {
    "housing": 347,
    "downtown": 263,
    "uvm-colleges": 236,
    "lake-outdoors": 142,
    "weather": 208,
    "food-drink": 261,
    "arts-music": 256,
    "politics": 395,
    "transportation": 171,
    "public-safety": 263,
    "business": 446,
    "sports": 103
  }
}
